{
	"configurations" : 
	[
		{
			"abstractTargets" : [],
			"directories" : 
			[
				{
					"build" : ".",
					"jsonFile" : "directory-.-Debug-f6f22219c74102c3da70.json",
					"minimumCMakeVersion" : 
					{
						"string" : "3.20"
					},
					"projectIndex" : 0,
					"source" : ".",
					"targetIndexes" : 
					[
						0
					]
				}
			],
			"name" : "Debug",
			"projects" : 
			[
				{
					"directoryIndexes" : 
					[
						0
					],
					"name" : "FarmBot",
					"targetIndexes" : 
					[
						0
					]
				}
			],
			"targets" : 
			[
				{
					"directoryIndex" : 0,
					"id" : "FarmBot::@6890427a1f51a3e7e1df",
					"jsonFile" : "target-FarmBot-Debug-1d0f9a62bfeee487f14e.json",
					"name" : "FarmBot",
					"projectIndex" : 0
				}
			]
		}
	],
	"kind" : "codemodel",
	"paths" : 
	{
		"build" : "C:/Users/boss_/source/repos/FamBot/out/build/x64-Debug",
		"source" : "C:/Users/boss_/source/repos/FamBot"
	},
	"version" : 
	{
		"major" : 2,
		"minor" : 9
	}
}
